nmtextprocessor1/__init__.py
nmtextprocessor1/processor.py
nmtextprocessor1-0.1.0.dist-info/METADATA
nmtextprocessor1-0.1.0.dist-info/WHEEL
nmtextprocessor1-0.1.0.dist-info/top_level.txt
nmtextprocessor1-0.1.0.dist-info/RECORD
