Metadata-Version: 2.1
Name: nmtextprocessor1
Version: 0.1.0
Summary: A text processing library for various NLP tasks
Author: Nidhi Mahandru
Author-email: nidhimahendru@gmail.com
Classifier: Programming Language :: Python :: 3
Classifier: License :: OSI Approved :: MIT License
Classifier: Operating System :: OS Independent
Requires-Python: >=3.7
